missing_101703139/missing.py
missing_101703139-1.0.2.dist-info/LICENSE
missing_101703139-1.0.2.dist-info/METADATA
missing_101703139-1.0.2.dist-info/WHEEL
missing_101703139-1.0.2.dist-info/entry_points.txt
missing_101703139-1.0.2.dist-info/top_level.txt
missing_101703139-1.0.2.dist-info/RECORD
